azure_auth_pgbouncer.py
azure_auth_pgbouncer-0.2.1.dist-info/METADATA
azure_auth_pgbouncer-0.2.1.dist-info/WHEEL
azure_auth_pgbouncer-0.2.1.dist-info/entry_points.txt
azure_auth_pgbouncer-0.2.1.dist-info/RECORD
