Metadata-Version: 2.3
Name: azure-auth-pgbouncer
Version: 0.2.1
Summary: 
License: MIT
Author: Maciej Małecki
Author-email: me@mmalecki.com
Requires-Python: >=3.12
Classifier: License :: OSI Approved :: MIT License
Classifier: Programming Language :: Python :: 3
Classifier: Programming Language :: Python :: 3.12
Classifier: Programming Language :: Python :: 3.13
Requires-Dist: azure-identity (>=1.21.0,<2.0.0)
